luxorasap/__init__.py
luxorasap/btgapi/__init__.py
luxorasap/btgapi/auth.py
luxorasap/btgapi/reports.py
luxorasap/btgapi/trades.py
luxorasap/datareader/__init__.py
luxorasap/datareader/core.py
luxorasap/ingest/__init__.py
luxorasap/ingest/cloud/__init__.py
luxorasap/ingest/legacy_local/dataloader.py
luxorasap/utils/__init__.py
luxorasap/utils/dataframe/__init__.py
luxorasap/utils/dataframe/reader.py
luxorasap/utils/dataframe/transforms.py
luxorasap/utils/storage/__init__.py
luxorasap/utils/storage/blob.py
luxorasap/utils/storage/change_tracker.py
luxorasap/utils/tools/__init__.py
luxorasap/utils/tools/excel.py
luxorasap-1.0.2.dist-info/METADATA
luxorasap-1.0.2.dist-info/WHEEL
luxorasap-1.0.2.dist-info/entry_points.txt
luxorasap-1.0.2.dist-info/top_level.txt
luxorasap-1.0.2.dist-info/RECORD
